{"width":512,"imagePath":"haigui_shadow_tex.png","height":1024,"name":"haigui_shadow","SubTexture":[{"y":804,"frameX":-436,"frameHeight":765,"frameY":-354,"width":158,"frameWidth":1020,"height":109,"name":"00013","x":1},{"y":683,"frameX":-436,"frameHeight":765,"frameY":-327,"width":153,"frameWidth":1020,"height":119,"name":"00003","x":1},{"y":132,"frameX":-436,"frameHeight":765,"frameY":-355,"width":157,"frameWidth":1020,"height":98,"name":"00012","x":159},{"y":1,"frameX":-442,"frameHeight":765,"frameY":-321,"width":156,"frameWidth":1020,"height":154,"name":"00005","x":1},{"y":232,"frameX":-436,"frameHeight":765,"frameY":-355,"width":157,"frameWidth":1020,"height":94,"name":"00011","x":157},{"y":1,"frameX":-438,"frameHeight":765,"frameY":-346,"width":157,"frameWidth":1020,"height":125,"name":"00014","x":318},{"y":128,"frameX":-439,"frameHeight":765,"frameY":-356,"width":158,"frameWidth":1020,"height":95,"name":"00008","x":318},{"y":423,"frameX":-437,"frameHeight":765,"frameY":-356,"width":157,"frameWidth":1020,"height":92,"name":"00010","x":153},{"y":560,"frameX":-441,"frameHeight":765,"frameY":-346,"width":160,"frameWidth":1020,"height":121,"name":"00006","x":1},{"y":428,"frameX":-441,"frameHeight":765,"frameY":-323,"width":150,"frameWidth":1020,"height":130,"name":"00002","x":1},{"y":915,"frameX":-440,"frameHeight":765,"frameY":-356,"width":159,"frameWidth":1020,"height":100,"name":"00007","x":1},{"y":1,"frameX":-438,"frameHeight":765,"frameY":-344,"width":157,"frameWidth":1020,"height":129,"name":"00000","x":159},{"y":157,"frameX":-440,"frameHeight":765,"frameY":-331,"width":154,"frameWidth":1020,"height":137,"name":"00001","x":1},{"y":296,"frameX":-442,"frameHeight":765,"frameY":-323,"width":150,"frameWidth":1020,"height":130,"name":"00004","x":1},{"y":328,"frameX":-438,"frameHeight":765,"frameY":-356,"width":157,"frameWidth":1020,"height":93,"name":"00009","x":153}]}