{"frameRate":24,"name":"effect_frame5","version":"5.5","compatibleVersion":"5.5","armature":[{"type":"Armature","frameRate":24,"name":"effect_frame5","aabb":{"x":-72.5,"y":-72.41,"width":145,"height":191.92},"bone":[{"name":"root"},{"name":"liuguang00011","parent":"root","transform":{"x":-55.9952,"y":-20.6526,"scX":-1}},{"name":"bone","parent":"root","transform":{"x":1.0264,"y":53.6826,"scX":0.6,"scY":0.6}},{"name":"liuguang0001","parent":"root","transform":{"x":56.1268,"y":-20.6526}},{"name":"cb","parent":"root","transform":{"x":1.1639,"y":53.2306,"skX":0.0254,"skY":0.0254,"scX":0.5,"scY":0.5}},{"name":"5","parent":"root","transform":{"y":-0.4111}},{"name":"bone1","parent":"root","transform":{"x":1.0264,"y":53.6826,"scX":-0.6,"scY":0.6}},{"name":"hb1111","parent":"bone","transform":{"x":29.626,"y":3.0419,"skX":-50.2987,"skY":-50.2987}},{"name":"hb","parent":"bone","transform":{"x":29.626,"y":3.0419,"scX":0.8737,"scY":0.8737}},{"name":"hb12","parent":"bone1","transform":{"x":29.626,"y":3.0419,"skX":23.0995,"skY":23.0995,"scX":1.1792,"scY":1.1792}},{"name":"hb112","parent":"bone1","transform":{"x":29.626,"y":3.0419,"skX":107.2729,"skY":107.2729}},{"name":"hb2","parent":"bone1","transform":{"x":29.626,"y":3.0419,"scX":0.8737,"scY":0.8737}},{"name":"hb11","parent":"bone","transform":{"x":29.626,"y":3.0419,"skX":107.2729,"skY":107.2729}},{"name":"hb111","parent":"bone","transform":{"x":29.626,"y":3.0419,"skX":-38.2913,"skY":-38.2913,"scX":0.8737,"scY":0.8737}},{"name":"hb1112","parent":"bone1","transform":{"x":29.626,"y":3.0419,"skX":-38.2913,"skY":-38.2913,"scX":0.8737,"scY":0.8737}},{"name":"hb11112","parent":"bone1","transform":{"x":29.626,"y":3.0419,"skX":-50.2987,"skY":-50.2987}},{"name":"hb111112","parent":"bone1","transform":{"x":29.626,"y":3.0419,"skX":23.0995,"skY":23.0995,"scX":1.1792,"scY":1.1792}},{"name":"hb1111111","parent":"bone1","transform":{"x":29.626,"y":3.0419,"skX":-50.2987,"skY":-50.2987}},{"name":"hb111111","parent":"bone","transform":{"x":29.626,"y":3.0419,"skX":-50.2987,"skY":-50.2987}},{"name":"hb1","parent":"bone","transform":{"x":29.626,"y":3.0419,"skX":23.0995,"skY":23.0995,"scX":1.1792,"scY":1.1792}},{"name":"hb11111","parent":"bone","transform":{"x":29.626,"y":3.0419,"skX":23.0995,"skY":23.0995,"scX":1.1792,"scY":1.1792}},{"length":12,"name":"jin0001","parent":"5","transform":{"x":0.0254,"y":-8.1341,"skX":-90,"skY":-90}}],"slot":[{"name":"5","parent":"5"},{"blendMode":"add","name":"cb","parent":"cb"},{"name":"hb","parent":"hb"},{"name":"hb1","parent":"hb1"},{"name":"hb11","parent":"hb11"},{"name":"hb111","parent":"hb111"},{"name":"hb1111","parent":"hb1111"},{"name":"hb11111","parent":"hb11111"},{"name":"hb111111","parent":"hb111111"},{"name":"hb2","parent":"hb2"},{"name":"hb12","parent":"hb12"},{"name":"hb112","parent":"hb112"},{"name":"hb1112","parent":"hb1112"},{"name":"hb11112","parent":"hb11112"},{"name":"hb111112","parent":"hb111112"},{"name":"hb1111111","parent":"hb1111111"},{"displayIndex":7,"name":"liuguang0001","parent":"liuguang0001"},{"displayIndex":7,"name":"liuguang00011","parent":"liuguang00011"},{"blendMode":"add","displayIndex":7,"name":"jin0001","parent":"jin0001"}],"skin":[{"slot":[{"name":"hb11","display":[{"name":"hb","transform":{"x":-0.1,"y":-0.01}}]},{"name":"hb11111","display":[{"name":"hb","transform":{"x":-0.1,"y":-0.01}}]},{"name":"hb12","display":[{"name":"hb","transform":{"x":-0.1,"y":-0.01}}]},{"name":"hb1111","display":[{"name":"hb","transform":{"x":-0.1,"y":-0.01}}]},{"name":"hb1111111","display":[{"name":"hb","transform":{"x":-0.1,"y":-0.01}}]},{"name":"hb111111","display":[{"name":"hb","transform":{"x":-0.1,"y":-0.01}}]},{"name":"hb111112","display":[{"name":"hb","transform":{"x":-0.1,"y":-0.01}}]},{"name":"hb11112","display":[{"name":"hb","transform":{"x":-0.1,"y":-0.01}}]},{"name":"hb1","display":[{"name":"hb","transform":{"x":-0.1,"y":-0.01}}]},{"name":"hb111","display":[{"name":"hb","transform":{"x":-0.1,"y":-0.01}}]},{"name":"liuguang00011","display":[{"name":"liuguang0024"},{"name":"liuguang0023"},{"name":"liuguang0022"},{"name":"liuguang0021"},{"name":"liuguang0020"},{"name":"liuguang0019"},{"name":"liuguang0018"},{"name":"liuguang0017"},{"name":"liuguang0016"},{"name":"liuguang0015"},{"name":"liuguang0014"},{"name":"liuguang0013"},{"name":"liuguang0012"},{"name":"liuguang0011"},{"name":"liuguang0010"},{"name":"liuguang0009"},{"name":"liuguang0008"},{"name":"liuguang0007"},{"name":"liuguang0006"},{"name":"liuguang0005"},{"name":"liuguang0004"},{"name":"liuguang0003"},{"name":"liuguang0002"},{"name":"liuguang0001"}]},{"name":"hb112","display":[{"name":"hb","transform":{"x":-0.1,"y":-0.01}}]},{"name":"liuguang0001","display":[{"name":"liuguang0024"},{"name":"liuguang0023"},{"name":"liuguang0022"},{"name":"liuguang0021"},{"name":"liuguang0020"},{"name":"liuguang0019"},{"name":"liuguang0018"},{"name":"liuguang0017"},{"name":"liuguang0016"},{"name":"liuguang0015"},{"name":"liuguang0014"},{"name":"liuguang0013"},{"name":"liuguang0012"},{"name":"liuguang0011"},{"name":"liuguang0010"},{"name":"liuguang0009"},{"name":"liuguang0008"},{"name":"liuguang0007"},{"name":"liuguang0006"},{"name":"liuguang0005"},{"name":"liuguang0004"},{"name":"liuguang0003"},{"name":"liuguang0002"},{"name":"liuguang0001"}]},{"name":"hb2","display":[{"name":"hb","transform":{"x":-0.1,"y":-0.01}}]},{"name":"5","display":[{"name":"4-5"}]},{"name":"cb","display":[{"name":"cb","transform":{"x":2.23,"y":1.56}}]},{"name":"jin0001","display":[{"name":"jin0008","transform":{"x":-10.7,"y":0.15,"skX":90,"skY":90}},{"name":"jin0007","transform":{"x":-10.7,"y":0.15,"skX":90,"skY":90}},{"name":"jin0006","transform":{"x":-10.7,"y":0.15,"skX":90,"skY":90}},{"name":"jin0005","transform":{"x":-10.7,"y":0.15,"skX":90,"skY":90}},{"name":"jin0004","transform":{"x":-10.7,"y":0.15,"skX":90,"skY":90}},{"name":"jin0003","transform":{"x":-10.7,"y":0.15,"skX":90,"skY":90}},{"name":"jin0002","transform":{"x":-10.7,"y":0.15,"skX":90,"skY":90}},{"name":"jin0001","transform":{"x":-10.7,"y":0.15,"skX":90,"skY":90}}]},{"name":"hb","display":[{"name":"hb","transform":{"x":-0.1,"y":-0.01}}]},{"name":"hb1112","display":[{"name":"hb","transform":{"x":-0.1,"y":-0.01}}]}]}],"animation":[{"duration":32,"playTimes":0,"name":"newAnimation","bone":[{"name":"cb","scaleFrame":[{"duration":17,"tweenEasing":0},{"duration":15,"tweenEasing":0,"x":0.84},{"duration":0}]},{"name":"bone","rotateFrame":[{"duration":32,"rotate":-7.75}],"scaleFrame":[{"duration":32,"x":1.1,"y":1.1}]},{"name":"hb","translateFrame":[{"duration":32,"tweenEasing":0},{"duration":0,"x":48.31,"y":-33.24}],"rotateFrame":[{"duration":32,"tweenEasing":0},{"duration":0,"rotate":-80.71}]},{"name":"hb1","translateFrame":[{"duration":15,"tweenEasing":0,"x":29.19,"y":-6.15},{"x":53.89,"y":-11.35},{"duration":16,"tweenEasing":0},{"duration":0,"x":26.94,"y":-5.68}],"rotateFrame":[{"duration":15,"tweenEasing":0,"rotate":37.27},{"rotate":68.8},{"duration":16,"tweenEasing":0},{"duration":0,"rotate":34.4}]},{"name":"hb11","translateFrame":[{"duration":11,"tweenEasing":0,"x":18.88,"y":-8.19},{"x":28.32,"y":-12.28},{"duration":20,"tweenEasing":0},{"duration":0,"x":17.7,"y":-7.68}],"rotateFrame":[{"duration":11,"tweenEasing":0,"rotate":-7.62},{"rotate":-11.44},{"duration":20,"tweenEasing":0},{"duration":0,"rotate":-7.15}]},{"name":"hb111","translateFrame":[{"duration":23,"tweenEasing":0,"x":11.04,"y":2.1},{"x":37.84,"y":7.21},{"duration":8,"tweenEasing":0},{"duration":0,"x":9.46,"y":1.8}],"rotateFrame":[{"duration":23,"tweenEasing":0,"rotate":42.5},{"rotate":145.73},{"duration":8,"tweenEasing":0},{"duration":0,"rotate":36.43}]},{"name":"hb1111","translateFrame":[{"duration":3,"tweenEasing":0,"x":39.06,"y":-1.47},{"x":42.61,"y":-1.6},{"duration":28,"tweenEasing":0},{"duration":0,"x":37.28,"y":-1.4}],"rotateFrame":[{"duration":3,"tweenEasing":0,"rotate":-131.83},{"rotate":-143.81},{"duration":28,"tweenEasing":0},{"duration":0,"rotate":-125.84}]},{"name":"hb11111","translateFrame":[{"duration":19,"tweenEasing":0,"x":18.76,"y":-7.94},{"x":45.04,"y":-19.05},{"duration":12,"tweenEasing":0},{"duration":0,"x":16.89,"y":-7.15}],"rotateFrame":[{"duration":19,"tweenEasing":0,"rotate":66},{"rotate":158.4},{"duration":12,"tweenEasing":0},{"duration":0,"rotate":59.4}]},{"name":"hb111111","translateFrame":[{"duration":7,"tweenEasing":0,"x":50.32,"y":-7.79},{"x":63.56,"y":-9.84},{"duration":24,"tweenEasing":0},{"duration":0,"x":47.67,"y":-7.38}],"rotateFrame":[{"duration":7,"tweenEasing":0,"rotate":-38.54},{"rotate":-48.68},{"duration":24,"tweenEasing":0},{"duration":0,"rotate":-36.51}]},{"name":"bone1","rotateFrame":[{"duration":32,"rotate":5.79}],"scaleFrame":[{"duration":32,"x":1.1,"y":1.1}]},{"name":"hb2","translateFrame":[{"duration":32,"tweenEasing":0},{"duration":0,"x":48.31,"y":-33.24}],"rotateFrame":[{"duration":32,"tweenEasing":0},{"duration":0,"rotate":-80.71}]},{"name":"hb12","translateFrame":[{"duration":15,"tweenEasing":0,"x":29.19,"y":-6.15},{"x":53.89,"y":-11.35},{"duration":16,"tweenEasing":0},{"duration":0,"x":26.94,"y":-5.68}],"rotateFrame":[{"duration":15,"tweenEasing":0,"rotate":37.27},{"rotate":68.8},{"duration":16,"tweenEasing":0},{"duration":0,"rotate":34.4}]},{"name":"hb112","translateFrame":[{"duration":11,"tweenEasing":0,"x":18.88,"y":-8.19},{"x":28.32,"y":-12.28},{"duration":20,"tweenEasing":0},{"duration":0,"x":17.7,"y":-7.68}],"rotateFrame":[{"duration":11,"tweenEasing":0,"rotate":-7.62},{"rotate":-11.44},{"duration":20,"tweenEasing":0},{"duration":0,"rotate":-7.15}]},{"name":"hb1112","translateFrame":[{"duration":23,"tweenEasing":0,"x":11.04,"y":2.1},{"x":37.84,"y":7.21},{"duration":8,"tweenEasing":0},{"duration":0,"x":9.46,"y":1.8}],"rotateFrame":[{"duration":23,"tweenEasing":0,"rotate":42.5},{"rotate":145.73},{"duration":8,"tweenEasing":0},{"duration":0,"rotate":36.43}]},{"name":"hb11112","translateFrame":[{"duration":3,"tweenEasing":0,"x":39.06,"y":-1.47},{"x":42.61,"y":-1.6},{"duration":28,"tweenEasing":0},{"duration":0,"x":37.28,"y":-1.4}],"rotateFrame":[{"duration":3,"tweenEasing":0,"rotate":-131.83},{"rotate":-143.81},{"duration":28,"tweenEasing":0},{"duration":0,"rotate":-125.84}]},{"name":"hb111112","translateFrame":[{"duration":19,"tweenEasing":0,"x":18.76,"y":-7.94},{"x":45.04,"y":-19.05},{"duration":12,"tweenEasing":0},{"duration":0,"x":16.89,"y":-7.15}],"rotateFrame":[{"duration":19,"tweenEasing":0,"rotate":66},{"rotate":158.4},{"duration":12,"tweenEasing":0},{"duration":0,"rotate":59.4}]},{"name":"hb1111111","translateFrame":[{"duration":7,"tweenEasing":0,"x":50.32,"y":-7.79},{"x":63.56,"y":-9.84},{"duration":24,"tweenEasing":0},{"duration":0,"x":47.67,"y":-7.38}],"rotateFrame":[{"duration":7,"tweenEasing":0,"rotate":-38.54},{"rotate":-48.68},{"duration":24,"tweenEasing":0},{"duration":0,"rotate":-36.51}]}],"slot":[{"name":"hb","colorFrame":[{"duration":19},{"duration":13,"tweenEasing":0},{"duration":0,"value":{"aM":0}}]},{"name":"hb1","colorFrame":[{},{"duration":14,"tweenEasing":0},{"duration":17,"value":{"aM":0}}]},{"name":"hb11","colorFrame":[{"duration":11,"tweenEasing":0,"value":{"aM":80}},{"duration":20,"value":{"aM":0}},{"tweenEasing":0},{"duration":0,"value":{"aM":90}}]},{"name":"hb111","colorFrame":[{"duration":9},{"duration":14,"tweenEasing":0},{"duration":9,"value":{"aM":0}}]},{"name":"hb1111","colorFrame":[{"duration":3,"tweenEasing":0,"value":{"aM":20}},{"duration":20,"value":{"aM":0}},{"duration":9,"tweenEasing":0},{"duration":0,"value":{"aM":30}}]},{"name":"hb11111","colorFrame":[{"duration":5},{"duration":14,"tweenEasing":0},{"duration":13,"value":{"aM":0}}]},{"name":"hb111111","colorFrame":[{"duration":7,"tweenEasing":0,"value":{"aM":50}},{"duration":20,"value":{"aM":0}},{"duration":5,"tweenEasing":0},{"duration":0,"value":{"aM":60}}]},{"name":"hb2","colorFrame":[{"duration":19},{"duration":13,"tweenEasing":0},{"duration":0,"value":{"aM":0}}]},{"name":"hb12","colorFrame":[{},{"duration":14,"tweenEasing":0},{"duration":17,"value":{"aM":0}}]},{"name":"hb112","colorFrame":[{"duration":11,"tweenEasing":0,"value":{"aM":80}},{"duration":20,"value":{"aM":0}},{"tweenEasing":0},{"duration":0,"value":{"aM":90}}]},{"name":"hb1112","colorFrame":[{"duration":9},{"duration":14,"tweenEasing":0},{"duration":9,"value":{"aM":0}}]},{"name":"hb11112","colorFrame":[{"duration":3,"tweenEasing":0,"value":{"aM":20}},{"duration":20,"value":{"aM":0}},{"duration":9,"tweenEasing":0},{"duration":0,"value":{"aM":30}}]},{"name":"hb111112","colorFrame":[{"duration":5},{"duration":14,"tweenEasing":0},{"duration":13,"value":{"aM":0}}]},{"name":"hb1111111","colorFrame":[{"duration":7,"tweenEasing":0,"value":{"aM":50}},{"duration":20,"value":{"aM":0}},{"duration":5,"tweenEasing":0},{"duration":0,"value":{"aM":60}}]},{"name":"liuguang0001","displayFrame":[{"value":23},{"duration":2,"value":22},{"value":21},{"value":20},{"value":19},{"value":18},{"value":17},{"duration":2,"value":16},{"value":15},{"value":14},{"duration":2,"value":13},{"value":12},{"value":11},{"value":10},{"value":9},{"value":8},{"duration":2,"value":7},{"value":6},{"value":5},{"duration":2,"value":4},{"value":3},{"value":2},{"value":1},{},{"duration":3,"value":-1}]},{"name":"liuguang00011","displayFrame":[{"value":23},{"duration":2,"value":22},{"value":21},{"value":20},{"value":19},{"value":18},{"value":17},{"duration":2,"value":16},{"value":15},{"value":14},{"duration":2,"value":13},{"value":12},{"value":11},{"value":10},{"value":9},{"value":8},{"duration":2,"value":7},{"value":6},{"value":5},{"duration":2,"value":4},{"value":3},{"value":2},{"value":1},{},{"duration":3,"value":-1}]},{"name":"jin0001","displayFrame":[{"duration":4,"value":7},{"duration":5,"value":6},{"duration":4,"value":5},{"duration":4,"value":4},{"duration":3,"value":3},{"duration":5,"value":2},{"duration":4,"value":1},{"duration":3}]}]}],"defaultActions":[{"gotoAndPlay":"newAnimation"}],"canvas":{"width":180,"height":180}}]}